easy_utils_dev/EasySsh.py
easy_utils_dev/Events.py
easy_utils_dev/FastQueue.py
easy_utils_dev/NameObject.py
easy_utils_dev/__init__.py
easy_utils_dev/abortable.py
easy_utils_dev/brevosmtp.py
easy_utils_dev/check_license.py
easy_utils_dev/cplib.py
easy_utils_dev/custom_env.py
easy_utils_dev/debugger.py
easy_utils_dev/easy_oracle.py
easy_utils_dev/encryptor.py
easy_utils_dev/ept.py
easy_utils_dev/exceptions.py
easy_utils_dev/filescompressor.py
easy_utils_dev/generate_license.py
easy_utils_dev/keycloakapi.py
easy_utils_dev/lralib.py
easy_utils_dev/ne1830PSS.py
easy_utils_dev/nsp_kafka.py
easy_utils_dev/openid_server.py
easy_utils_dev/optics_utils.py
easy_utils_dev/require_auth.py
easy_utils_dev/simple_sqlite.py
easy_utils_dev/temp_memory.py
easy_utils_dev/uiserver-VM026441.py
easy_utils_dev/uiserver.py
easy_utils_dev/utils.py
easy_utils_dev/winserviceapi.py
easy_utils_dev/wsnoclib.py
easy_utils_dev/wsselib.py
easy_utils_dev/ept_sql/create_dirs.sql
easy_utils_dev/ept_sql/create_ept_tables.sql
easy_utils_dev-2.173.dist-info/METADATA
easy_utils_dev-2.173.dist-info/WHEEL
easy_utils_dev-2.173.dist-info/top_level.txt
easy_utils_dev-2.173.dist-info/RECORD
