Metadata-Version: 2.4
Name: easy_utils_dev
Version: 2.173
Keywords: python3
Classifier: Programming Language :: Python :: 3
Requires-Dist: psutil
Requires-Dist: ping3
Requires-Dist: snakebite-py3
Requires-Dist: flask
Requires-Dist: flask_cors
Requires-Dist: xmltodict
Requires-Dist: paramiko
Requires-Dist: oracledb
Requires-Dist: requests
Requires-Dist: flask_socketio
Requires-Dist: python-dotenv
Requires-Dist: gevent
Requires-Dist: pyzipper
Requires-Dist: pyjwt
Requires-Dist: authlib
Requires-Dist: kafka-python
Dynamic: classifier
Dynamic: keywords
Dynamic: requires-dist
